filters/__init__.py
filters/base.py
filters/complex.py
filters/extensions.py
filters/handlers.py
filters/macros.py
filters/number.py
filters/simple.py
filters/string.py
filters/test.py
filters-1.3.2.dist-info/DESCRIPTION.rst
filters-1.3.2.dist-info/METADATA
filters-1.3.2.dist-info/RECORD
filters-1.3.2.dist-info/WHEEL
filters-1.3.2.dist-info/metadata.json
filters-1.3.2.dist-info/top_level.txt
