Metadata-Version: 1.1
Name: filters
Version: 1.3.2
Summary: Validation and data pipelines made easy!
Home-page: https://filters.readthedocs.io/
Author: Phoenix Zerin
Author-email: phoenix.zerin@eflglobal.com
License: MIT
Keywords: data validation
Platform: UNKNOWN
Classifier: Development Status :: 5 - Production/Stable
Classifier: Intended Audience :: Developers
Classifier: License :: OSI Approved :: MIT License
Classifier: Programming Language :: Python :: 2
Classifier: Programming Language :: Python :: 2.7
Classifier: Programming Language :: Python :: 3
Classifier: Programming Language :: Python :: 3.5
Classifier: Programming Language :: Python :: 3.6
Classifier: Topic :: Software Development :: Libraries :: Python Modules
Classifier: Topic :: Text Processing :: Filters
